LICENSE
MANIFEST.in
README.md
qoma_smuggler.py
setup.cfg
setup.py
notebooks/0_Example_HelloJupyterNotebook.ipynb
notebooks/1_Example_ReadFAMEdatabase.ipynb
notebooks/2_Example_Accessing_4GL.ipynb
notebooks/3_Example_DateRangeConversion.ipynb
notebooks/4_Example_WriteFAMEdatabase.ipynb
notebooks/5_Example_WriteFAMEdatabase.ipynb
notebooks/6_Example_Read_Write_4GL_Peek.ipynb
qoma_smuggler.egg-info/PKG-INFO
qoma_smuggler.egg-info/SOURCES.txt
qoma_smuggler.egg-info/dependency_links.txt
qoma_smuggler.egg-info/requires.txt
qoma_smuggler.egg-info/top_level.txt
scripts/smuggler_test.py