Metadata-Version: 1.0
Name: qoma-smuggler
Version: 0.0.4
Summary: Transport Data and Commands Across the FAME / Python Border
Home-page: http://github.com/qomaio
Author: Qoma LLC
Author-email: info@qoma.io
License: AGPLv3
Platform: any
